new_year_2026/__init__.py
new_year_2026/ctypes_shared/README.md
new_year_2026/ctypes_shared/__init__.py
new_year_2026/ctypes_shared/hello.c
new_year_2026/ctypes_shared/hello_ctypes.py
new_year_2026/ctypes_shared/libhello.so
new_year_2026/hello_ext/__init__.py
new_year_2026/hello_ext/_core.cpython-39-x86_64-linux-gnu.so
new_year_2026/hello_ext/bindings.cpp
new_year_2026/hello_ext/hello_c.c
new_year_2026/hello_ext/hello_c.h
new_year_2026/hello_ext/hello_cpp.cpp
new_year_2026/hello_ext/hello_cpp.h
new_year_2026/tcp_tls/__init__.py
new_year_2026/tcp_tls/cert.pem
new_year_2026/tcp_tls/get_or_post.py
new_year_2026/tcp_tls/key.pem
new_year_2026/tcp_tls/mini_tls_server.py
new_year_2026/tcp_tls/ssh_minimal_client.py
new_year_2026/tcp_tls/tcp_client.py
new_year_2026/tcp_tls/tcp_server.py
new_year_2026/tcp_tls/tls_echo_client.py
new_year_2026/tcp_tls/tls_echo_server.py
new_year_2026-1.1.27.dist-info/METADATA
new_year_2026-1.1.27.dist-info/WHEEL
new_year_2026-1.1.27.dist-info/top_level.txt
new_year_2026-1.1.27.dist-info/RECORD
