Metadata-Version: 2.4
Name: new_year_2026
Version: 1.1.27
Summary: TCP/TLS/HTTP/SSH learning scripts and demos.
Author-email: Tao Bo <taobo@example.com>
License: MIT
Requires-Python: >=3.9
